busradar24/__init__.py
busradar24/bus.py
busradar24-0.1.0.dist-info/LICENSE
busradar24-0.1.0.dist-info/METADATA
busradar24-0.1.0.dist-info/WHEEL
busradar24-0.1.0.dist-info/RECORD
