Metadata-Version: 2.3
Name: busradar24
Version: 0.1.0
Summary: A package to get the location of busses
License: MIT
Author: Pinguin
Author-email: jonathan.krueger@teckids.org
Requires-Python: >=3.13
Classifier: License :: OSI Approved :: MIT License
Classifier: Programming Language :: Python :: 3
Classifier: Programming Language :: Python :: 3.13
Requires-Dist: requests (>=2.32.3,<3.0.0)
Project-URL: Issues, https://codeberg.org/pinguin/BusRadar24/issues
Project-URL: Repository, https://codeberg.org/pinguin/BusRadar24.git
